MANIFEST.in
Makefile
README
setup.py
test/__init__.py
test/__init__.pyc
test/test_config.py
test/test_config.pyc
test/test_increment.py
test/test_increment.pyc
tiddlywebplugins/__init__.py
tiddlywebplugins/voting.py
tiddlywebplugins.voting.egg-info/PKG-INFO
tiddlywebplugins.voting.egg-info/SOURCES.txt
tiddlywebplugins.voting.egg-info/dependency_links.txt
tiddlywebplugins.voting.egg-info/namespace_packages.txt
tiddlywebplugins.voting.egg-info/not-zip-safe
tiddlywebplugins.voting.egg-info/requires.txt
tiddlywebplugins.voting.egg-info/top_level.txt