Metadata-Version: 1.0
Name: tiddlywebplugins.voting
Version: 0.251
Summary: UNKNOWN
Home-page: http://pypi.python.org/pypi/tiddlywebplugins.voting
Author: Jon Robson
Author-email: jdlrobson@gmail.com
License: UNKNOWN
Platform: Posix; MacOS X; Windows
